dbt/adapters/proton/__init__.py
dbt/adapters/proton/__version__.py
dbt/adapters/timeplus/__init__.py
dbt/adapters/timeplus/__version__.py
dbt/adapters/timeplus/column.py
dbt/adapters/timeplus/connections.py
dbt/adapters/timeplus/impl.py
dbt/adapters/timeplus/relation.py
dbt/include/timeplus/__init__.py
dbt/include/timeplus/dbt_project.yml
dbt/include/timeplus/macros/adapters.sql
dbt/include/timeplus/macros/catalog.sql
dbt/include/timeplus/macros/generic_test_sql/accepted_values.sql
dbt/include/timeplus/macros/generic_test_sql/not_null.sql
dbt/include/timeplus/macros/generic_test_sql/relationships.sql
dbt/include/timeplus/macros/generic_test_sql/unique.sql
dbt/include/timeplus/macros/materializations/incremental.sql
dbt/include/timeplus/macros/materializations/materialized_view.sql
dbt/include/timeplus/macros/materializations/seed.sql
dbt/include/timeplus/macros/materializations/snapshot.sql
dbt/include/timeplus/macros/materializations/test.sql
dbt/include/timeplus/macros/operations/setup_kafka_clickhouse.sql
dbt/include/timeplus/macros/schema_tests/relationships.sql
dbt_timeplus-1.10.2.dist-info/licenses/LICENSE
dbt_timeplus-1.10.2.dist-info/METADATA
dbt_timeplus-1.10.2.dist-info/WHEEL
dbt_timeplus-1.10.2.dist-info/entry_points.txt
dbt_timeplus-1.10.2.dist-info/top_level.txt
dbt_timeplus-1.10.2.dist-info/RECORD
