Metadata-Version: 2.4
Name: dbt-timeplus
Version: 1.10.2
Summary: The Timeplus (Proton) plugin for dbt (data build tool)
Home-page: https://github.com/timeplus-io/dbt-timeplus
Author: Timeplus Inc.
Author-email: dev@timeplus.com
License: Apache 2.0 License
Platform: any
Classifier: Development Status :: 5 - Production/Stable
Classifier: License :: OSI Approved :: Apache Software License
Classifier: Operating System :: Microsoft :: Windows
Classifier: Operating System :: MacOS :: MacOS X
Classifier: Operating System :: POSIX :: Linux
Classifier: Programming Language :: Python :: 3.10
Classifier: Programming Language :: Python :: 3.11
Classifier: Programming Language :: Python :: 3.12
Requires-Python: >=3.10
License-File: LICENSE
Requires-Dist: dbt-core==1.10.13
Requires-Dist: proton-driver>=0.2.13
Dynamic: author
Dynamic: author-email
Dynamic: classifier
Dynamic: description
Dynamic: description-content-type
Dynamic: home-page
Dynamic: license
Dynamic: license-file
Dynamic: platform
Dynamic: requires-dist
Dynamic: requires-python
Dynamic: summary
